Workbook

Sheet Transactions
A2: Transactions | B2: Month | N2: Annual Amount
B3: January | C3: February | D3: March | E3: April | F3: May | G3: June | H3: July | I3: August | J3: September | K3: October | L3: November | M3: December
A4: SALES
A5: Cash sales | N5: =SUM(B5:M5) -> 0
A6: Credit sales | N6: =SUM(B6:M6) -> 0
A7: Sales of the month | B7: =B5+B6 -> 0 | C7: =C5+C6 -> 0 | D7: =D5+D6 -> 0 | E7: =E5+E6 -> 0 | F7: =F5+F6 -> 0 | G7: =G5+G6 -> 0 | H7: =H5+H6 -> 0 | I7: =I5+I6 -> 0 | ... M7: =M5+M6 -> 0 | N7: =SUM(B7:M7) -> 0
A9: PURCHASES
A10: Cash purchases | N10: =SUM(B10:M10) -> 0
A11: Credit purchases | C11: =Transactions!C7+Transactions!C36+Transactions!C43+(Transactions!C7-Transactions!C46) -> 0 | D11: =Transactions!D7+Transactions!D36+Transactions!D43+(Transactions!D7-Transactions!D46) -> 0 | E11: =Transactions!E7+Transactions!E36+Transactions!E43+(Transactions!E7-Transactions!E46) -> 0 | F11: =Transactions!F7+Transactions!F36+Transactions!F43+(Transactions!F7-Transactions!F46) -> 0 | G11: =Transactions!G7+Transactions!G36+Transactions!G43+(Transactions!G7-Transactions!G46) -> 0 | H11: =Transactions!H7+Transactions!H36+Transactions!H43+(Transactions!H7-Transactions!H46) -> 0 | I11: =Transactions!I7+Transactions!I36+Transactions!I43+(Transactions!I7-Transactions!I46) -> 0 | J11: =Transactions!J7+Transactions!J36+Transactions!J43+(Transactions!J7-Transactions!J46) -> 0 | ... M11: =Transactions!M7+Transactions!M36+Transactions!M43+(Transactions!M7-Transactions!M46) -> 0 | N11: =SUM(B11:M11) -> 0
A12: Purchase of the month | B12: =B10+B11 -> 0 | C12: =C10+C11 -> 0 | D12: =D10+D11 -> 0 | E12: =E10+E11 -> 0 | F12: =F10+F11 -> 0 | G12: =G10+G11 -> 0 | H12: =H10+H11 -> 0 | I12: =I10+I11 -> 0 | ... M12: =M10+M11 -> 0 | N12: =SUM(B12:M12) -> 0
A14: OPERATING EXPENSES
A15: Salaries | N15: =SUM(B15:M15) -> 0
A16: Travel costs | N16: =SUM(B16:M16) -> 0
A17: Rent | N17: =SUM(B17:M17) -> 0
A18: Insurance | N18: =SUM(B18:M18) -> 0
A19: Repairs and maintenance | N19: =SUM(B19:M19) -> 0
A20: Office supplies | N20: =SUM(B20:M20) -> 0
A21: Advertising and marketing | N21: =SUM(B21:M21) -> 0
A22: Electricity | N22: =SUM(B22:M22) -> 0
A23: Water | N23: =SUM(B23:M23) -> 0
A24: Phone and Internet | N24: =SUM(B24:M24) -> 0
A25: Fuel | N25: =SUM(B25:M25) -> 0
A26: Municipal Fees | N26: =SUM(B26:B26) -> 0
A27: Other Operating Expenses | N27: =SUM(B27:M27) -> 0
A28: Total Operating Expenses | B28: =SUM(B15:B27) -> 0 | C28: =SUM(C15:C27) -> 0 | D28: =SUM(D15:D27) -> 0 | E28: =SUM(E15:E27) -> 0 | F28: =SUM(F15:F27) -> 0 | G28: =SUM(G15:G27) -> 0 | H28: =SUM(H15:H27) -> 0 | I28: =SUM(I15:I27) -> 0 | ... M28: =SUM(M15:M27) -> 0 | N28: =SUM(B28:M28) -> 0
A30: FINANCIAL EXPENSES
A31: Interest Paid | N31: =SUM(B31:M31) -> 0
A33: CASH AND BANKS
A34: How much cash do you manage monthly? | N34: =SUM(B34:M34) -> 0
A35: Amount in bank current accounts | N35: =SUM(B35:M35) -> 0
A36: Total Cash | B36: =B34+B35 -> 0 | C36: =C34+C35 -> 0 | D36: =D34+D35 -> 0 | E36: =E34+E35 -> 0 | F36: =F34+F35 -> 0 | G36: =G34+G35 -> 0 | H36: =H34+H35 -> 0 | I36: =I34+I35 -> 0 | ... M36: =M34+M35 -> 0 | N36: =SUM(B36:M36) -> 0
A38: Amounts in deposit accounts > 1 year | N38: =SUM(B38:M38) -> 0
A40: ACCOUNTS RECIEVABLE
A41: Credit Sales from Customers | B41: =B7-B5 -> 0 | C41: =C7-C5 -> 0 | D41: =D7-D5 -> 0 | E41: =E7-E5 -> 0 | F41: =F7-F5 -> 0 | G41: =G7-G5 -> 0 | H41: =H7-H5 -> 0 | I41: =I7-I5 -> 0 | ... M41: =M7-M5 -> 0 | N41: =SUM(B41:M41) -> 0
A42: Other Receivables | N42: =SUM(B42:M42) -> 0
A43: Total Accounts Receivable | B43: =B41+B42 -> 0 | C43: =C41+C42 -> 0 | D43: =D41+D42 -> 0 | E43: =E41+E42 -> 0 | F43: =F41+F42 -> 0 | G43: =G41+G42 -> 0 | H43: =H41+H42 -> 0 | I43: =I41+I42 -> 0 | ... M43: =M41+M42 -> 0 | N43: =SUM(B43:M43) -> 0
A45: INVENTORY
A46: Inventory of goods | N46: =SUM(B46:M46) -> 0
A48: LIABILITIES
A49: Bank Loans < 12 months | N49: =SUM(B49:M49) -> 0
A50: With interest | N50: =SUM(B50:M50) -> 0
A51: Interest free (e.g., loans from friends and family) | N51: =SUM(B51:M51) -> 0
A52: Non Bank Loan <12months | N52: =SUM(B52:M52) -> 0
A53: Loans Payable < 12 months | B53: =B49+B52 -> 0 | C53: =C49+C52 -> 0 | D53: =D49+D52 -> 0 | E53: =E49+E52 -> 0 | F53: =F49+F52 -> 0 | G53: =G49+G52 -> 0 | H53: =H49+H52 -> 0 | I53: =I49+I52 -> 0 | ... M53: =M49+M52 -> 0 | N53: =SUM(B53:M53) -> 0
A54: Commissions due | N54: =SUM(B54:M54) -> 0
A55: Payment to providers (credit purchases) | N55: =SUM(B55:M55) -> 0
A56: Taxes and fees due | N56: =SUM(B56:M56) -> 0
A57: Pension Funds due | N57: =SUM(B57:M57) -> 0
A58: Total Accounts Payable | B58: =SUM(B53:B57) -> 0 | C58: =SUM(C53:C57) -> 0 | D58: =SUM(D53:D57) -> 0 | E58: =SUM(E53:E57) -> 0 | F58: =SUM(F53:F57) -> 0 | G58: =SUM(G53:G57) -> 0 | H58: =SUM(H53:H57) -> 0 | I58: =SUM(I53:I57) -> 0 | ... M58: =SUM(M53:M57) -> 0 | N58: =SUM(B58:M58) -> 0
A60: Bank Loans > 12 months | N60: =SUM(B60:M60) -> 0
A61: Non-Bank Loans > 12 months | N61: =SUM(B61:M61) -> 0
A62: Total Loans > 12 months | B62: =B60+B61 -> 0 | C62: =C60+C61 -> 0 | D62: =D60+D61 -> 0 | E62: =E60+E61 -> 0 | F62: =F60+F61 -> 0 | G62: =G60+G61 -> 0 | H62: =H60+H61 -> 0 | I62: =I60+I61 -> 0 | ... M62: =M60+M61 -> 0 | N62: =SUM(B62:M62) -> 0
A64: FIXED ASSETS
A65: Furniture | N65: =SUM(B65:M65) -> 0
A66: Machinery | N66: =SUM(B66:M66) -> 0
A67: Equipment | N67: =SUM(B67:M67) -> 0
A68: Vehicles | N68: =SUM(B68:M68) -> 0
A69: Land | N69: =SUM(B69:M69) -> 0
A70: Building | N70: =SUM(B70:M70) -> 0
A71: Total Fixed Assets | B71: =SUM(B65:B70) -> 0 | C71: =SUM(C65:C70) -> 0 | D71: =SUM(D65:D70) -> 0 | E71: =SUM(E65:E70) -> 0 | F71: =SUM(F65:F70) -> 0 | G71: =SUM(G65:G70) -> 0 | H71: =SUM(H65:H70) -> 0 | I71: =SUM(I65:I70) -> 0 | ... M71: =SUM(M65:M70) -> 0 | N71: =SUM(B71:M71) -> 0
A73: Total Assets | B73: =B71+B46+B36+B43 -> 0 | C73: =C71+C46+C36+C43 -> 0 | D73: =D71+D46+D36+D43 -> 0 | E73: =E71+E46+E36+E43 -> 0 | F73: =F71+F46+F36+F43 -> 0 | G73: =G71+G46+G36+G43 -> 0 | H73: =H71+H46+H36+H43 -> 0 | I73: =I71+I46+I36+I43 -> 0 | ... M73: =M71+M46+M36+M43 -> 0 | N73: =SUM(B73:M73) -> 0

Sheet FInancial Statements
A2: Categorisation | B2: Month | N2: Annual Amount
B3: January | C3: February | D3: March | E3: April | F3: May | G3: June | H3: July | I3: August | J3: September | K3: October | L3: November | M3: December
A4: Income Statement - summary
A5: Revenue | B5: =Transactions!B7 -> 0 | C5: =Transactions!C7 -> 0 | D5: =Transactions!D7 -> 0 | E5: =Transactions!E7 -> 0 | F5: =Transactions!F7 -> 0 | G5: =Transactions!G7 -> 0 | H5: =Transactions!H7 -> 0 | I5: =Transactions!I7 -> 0 | ... M5: =Transactions!M7 -> 0 | N5: =SUM(B5:M5) -> 0
A6: Less
A7: Expenses | B7: =Transactions!B12+Transactions!B28+Transactions!B31 -> 0 | C7: =Transactions!C12+Transactions!C28+Transactions!C31 -> 0 | D7: =Transactions!D12+Transactions!D28+Transactions!D31 -> 0 | E7: =Transactions!E12+Transactions!E28+Transactions!E31 -> 0 | F7: =Transactions!F12+Transactions!F28+Transactions!F31 -> 0 | G7: =Transactions!G12+Transactions!G28+Transactions!G31 -> 0 | H7: =Transactions!H12+Transactions!H28+Transactions!H31 -> 0 | I7: =Transactions!I12+Transactions!I28+Transactions!I31 -> 0 | ... M7: =Transactions!M12+Transactions!M28+Transactions!M31 -> 0 | N7: =SUM(B7:M7) -> 0
A8: Net income | B8: =B5-B7 -> 0 | C8: =C5-C7 -> 0 | D8: =D5-D7 -> 0 | E8: =E5-E7 -> 0 | F8: =F5-F7 -> 0 | G8: =G5-G7 -> 0 | H8: =H5-H7 -> 0 | I8: =I5-I7 -> 0 | ... M8: =M5-M7 -> 0 | N8: =SUM(B8:M8) -> 0
A10: Balance Sheet - summary
A11: Assets
A12: Current Assets | B12: =Transactions!B34+Transactions!B35+Transactions!B41+Transactions!B42+(Transactions!B7-Transactions!B46) -> 0 | C12: =Transactions!C34+Transactions!C35+Transactions!C41+Transactions!C42+(Transactions!C7-Transactions!C46) -> 0 | D12: =Transactions!D34+Transactions!D35+Transactions!D41+Transactions!D42+(Transactions!D7-Transactions!D46) -> 0 | E12: =Transactions!E34+Transactions!E35+Transactions!E41+Transactions!E42+(Transactions!E7-Transactions!E46) -> 0 | F12: =Transactions!F34+Transactions!F35+Transactions!F41+Transactions!F42+(Transactions!F7-Transactions!F46) -> 0 | G12: =Transactions!G34+Transactions!G35+Transactions!G41+Transactions!G42+(Transactions!G7-Transactions!G46) -> 0 | H12: =Transactions!H34+Transactions!H35+Transactions!H41+Transactions!H42+(Transactions!H7-Transactions!H46) -> 0 | I12: =Transactions!I34+Transactions!I35+Transactions!I41+Transactions!I42+(Transactions!I7-Transactions!I46) -> 0 | ... M12: =Transactions!M34+Transactions!M35+Transactions!M41+Transactions!M42+(Transactions!M7-Transactions!M46) -> 0 | N12: =SUM(B12:M12) -> 0
A13: Fixed Assets (non-current assets) | B13: =Transactions!B71 -> 0 | C13: =Transactions!C65+Transactions!C68+Transactions!C69 -> 0 | D13: =Transactions!D65+Transactions!D68+Transactions!D69 -> 0 | E13: =Transactions!E65+Transactions!E68+Transactions!E69 -> 0 | F13: =Transactions!F65+Transactions!F68+Transactions!F69 -> 0 | G13: =Transactions!G65+Transactions!G68+Transactions!G69 -> 0 | H13: =Transactions!H65+Transactions!H68+Transactions!H69 -> 0 | I13: =Transactions!I65+Transactions!I68+Transactions!I69 -> 0 | J13: =Transactions!J65+Transactions!J68+Transactions!J69 -> 0 | ... M13: =Transactions!M65+Transactions!M68+Transactions!M69 -> 0 | N13: =SUM(B13:M13) -> 0
A14: Total Assets | B14: =SUM(B12:B13) -> 0 | C14: =SUM(C12:C13) -> 0 | D14: =SUM(D12:D13) -> 0 | E14: =SUM(E12:E13) -> 0 | F14: =SUM(F12:F13) -> 0 | G14: =SUM(G12:G13) -> 0 | H14: =SUM(H12:H13) -> 0 | I14: =SUM(I12:I13) -> 0 | ... M14: =SUM(M12:M13) -> 0 | N14: =SUM(B14:M14) -> 0
A16: Liability and Equity
A17: Current Liability | B17: =Transactions!B58 -> 0 | C17: =Transactions!C58 -> 0 | D17: =Transactions!D58 -> 0 | E17: =Transactions!E58 -> 0 | F17: =Transactions!F58 -> 0 | G17: =Transactions!G58 -> 0 | H17: =Transactions!H58 -> 0 | I17: =Transactions!I58 -> 0 | ... M17: =Transactions!M58 -> 0 | N17: =SUM(B17:M17) -> 0
A18: Long Term Liability (non-current liability) | B18: =Transactions!B62 -> 0 | C18: =Transactions!C62 -> 0 | D18: =Transactions!D62 -> 0 | E18: =Transactions!E62 -> 0 | F18: =Transactions!F62 -> 0 | G18: =Transactions!G62 -> 0 | H18: =Transactions!H62 -> 0 | I18: =Transactions!I62 -> 0 | ... M18: =Transactions!M62 -> 0 | N18: =SUM(B18:M18) -> 0
A19: Equity | B19: =B14-B17-B18 -> 0 | C19: =C14-C17-C18 -> 0 | D19: =D14-D17-D18 -> 0 | E19: =E14-E17-E18 -> 0 | F19: =F14-F17-F18 -> 0 | G19: =G14-G17-G18 -> 0 | H19: =H14-H17-H18 -> 0 | I19: =I14-I17-I18 -> 0 | ... M19: =M14-M17-M18 -> 0 | N19: =SUM(B19:M19) -> 0
A20: Total Liability and Equity | B20: =SUM(B17:B19) -> 0 | C20: =SUM(C17:C19) -> 0 | D20: =SUM(D17:D19) -> 0 | E20: =SUM(E17:E19) -> 0 | F20: =SUM(F17:F19) -> 0 | G20: =SUM(G17:G19) -> 0 | H20: =SUM(H17:H19) -> 0 | I20: =SUM(I17:I19) -> 0 | ... M20: =SUM(M17:M19) -> 0 | N20: =SUM(B20:M20) -> 0
A22: Break-even | B22: =Transactions!B28/(1-(Transactions!B12/Transactions!B7)) -> #DIV/0! | C22: =Transactions!C28/(1-(Transactions!C12/Transactions!C7)) -> #DIV/0! | D22: =Transactions!D28/(1-(Transactions!D12/Transactions!D7)) -> #DIV/0! | E22: =Transactions!E28/(1-(Transactions!E12/Transactions!E7)) -> #DIV/0! | F22: =Transactions!F28/(1-(Transactions!F12/Transactions!F7)) -> #DIV/0! | G22: =Transactions!G28/(1-(Transactions!G12/Transactions!G7)) -> #DIV/0! | H22: =Transactions!H28/(1-(Transactions!H12/Transactions!H7)) -> #DIV/0! | I22: =Transactions!I28/(1-(Transactions!I12/Transactions!I7)) -> #DIV/0! | ... N22: =Transactions!N28/(1-(Transactions!N12/Transactions!N7)) -> #DIV/0!
A24: Cash flow
A25: Cash Flow | B25: =B8+Transactions!B31+Transactions!B55-Transactions!B43 -> 0 | C25: =C8+Transactions!C31+Transactions!C55-Transactions!C43 -> 0 | D25: =D8+Transactions!D31+Transactions!D55-Transactions!D43 -> 0 | E25: =E8+Transactions!E31+Transactions!E55-Transactions!E43 -> 0 | F25: =F8+Transactions!F31+Transactions!F55-Transactions!F43 -> 0 | G25: =G8+Transactions!G31+Transactions!G55-Transactions!G43 -> 0 | H25: =H8+Transactions!H31+Transactions!H55-Transactions!H43 -> 0 | I25: =I8+Transactions!I31+Transactions!I55-Transactions!I43 -> 0 | ... M25: =M8+Transactions!M31+Transactions!M55-Transactions!M43 -> 0 | N25: =SUM(B25:M25) -> 0
A27: Income Statement - detailed
A28: Sales | B28: =Transactions!B7 -> 0 | C28: =Transactions!C7 -> 0 | D28: =Transactions!D7 -> 0 | E28: =Transactions!E7 -> 0 | F28: =Transactions!F7 -> 0 | G28: =Transactions!G7 -> 0 | H28: =Transactions!H7 -> 0 | I28: =Transactions!I7 -> 0 | ... M28: =Transactions!M7 -> 0 | N28: =SUM(B28:M28) -> 0
A29: Less:
A30: Purchases | B30: =Transactions!B12 -> 0 | C30: =Transactions!C12 -> 0 | D30: =Transactions!D12 -> 0 | E30: =Transactions!E12 -> 0 | F30: =Transactions!F12 -> 0 | G30: =Transactions!G12 -> 0 | H30: =Transactions!H12 -> 0 | I30: =Transactions!I12 -> 0 | ... M30: =Transactions!M12 -> 0 | N30: =SUM(B30:M30) -> 0
A31: Gross Profit | B31: =B28-B30 -> 0 | C31: =C28-C30 -> 0 | D31: =D28-D30 -> 0 | E31: =E28-E30 -> 0 | F31: =F28-F30 -> 0 | G31: =G28-G30 -> 0 | H31: =H28-H30 -> 0 | I31: =I28-I30 -> 0 | ... M31: =M28-M30 -> 0 | N31: =SUM(B31:M31) -> 0
A32: Less:
A33: Operating expenses and Financial Expenses | B33: =Transactions!B28+Transactions!B31 -> 0 | C33: =Transactions!C28+Transactions!C31 -> 0 | D33: =Transactions!D28+Transactions!D31 -> 0 | E33: =Transactions!E28+Transactions!E31 -> 0 | F33: =Transactions!F28+Transactions!F31 -> 0 | G33: =Transactions!G28+Transactions!G31 -> 0 | H33: =Transactions!H28+Transactions!H31 -> 0 | I33: =Transactions!I28+Transactions!I31 -> 0 | ... M33: =Transactions!M28+Transactions!M31 -> 0 | N33: =SUM(B33:M33) -> 0
A34: Profit before tax | B34: =B31-B33 -> 0 | C34: =C31-C33 -> 0 | D34: =D31-D33 -> 0 | E34: =E31-E33 -> 0 | F34: =F31-F33 -> 0 | G34: =G31-G33 -> 0 | H34: =H31-H33 -> 0 | I34: =I31-I33 -> 0 | ... M34: =M31-M33 -> 0 | N34: =SUM(B34:M34) -> 0
A35: Less:
A36: Tax Expenses | B36: 0 | C36: 0 | D36: 0 | E36: 0 | F36: 0 | G36: 0 | H36: 0 | I36: 0 | J36: 0 | K36: 0 | L36: 0 | M36: 0 | N36: =SUM(B36:M36) -> 0
A37: Net Income | B37: =B34-B36 -> 0 | C37: =C34-C36 -> 0 | D37: =D34-D36 -> 0 | E37: =E34-E36 -> 0 | F37: =F34-F36 -> 0 | G37: =G34-G36 -> 0 | H37: =H34-H36 -> 0 | I37: =I34-I36 -> 0 | ... M37: =M34-M36 -> 0 | N37: =SUM(B37:M37) -> 0
A39: Balance Sheet - detailed
A40: A. Current Assets
A41: Total Cash | B41: =Transactions!B36+B25 -> 0 | C41: =Transactions!C36+C25 -> 0 | D41: =Transactions!D36+D25 -> 0 | E41: =Transactions!E36+E25 -> 0 | F41: =Transactions!F36+F25 -> 0 | G41: =Transactions!G36+G25 -> 0 | H41: =Transactions!H36+H25 -> 0 | I41: =Transactions!I36+I25 -> 0 | ... M41: =Transactions!M36+M25 -> 0 | N41: =SUM(B41:M41) -> 0
A42: Accounts Receivable | B42: =Transactions!B43 -> 0 | C42: =Transactions!C43 -> 0 | D42: =Transactions!D43 -> 0 | E42: =Transactions!E43 -> 0 | F42: =Transactions!F43 -> 0 | G42: =Transactions!G43 -> 0 | H42: =Transactions!H43 -> 0 | I42: =Transactions!I43 -> 0 | ... M42: =Transactions!M43 -> 0 | N42: =SUM(B42:M42) -> 0
A43: Inventory | B43: =Transactions!B46 -> 0 | N43: =SUM(B43:M43) -> 0
A44: Total Current Assets | B44: =SUM(B41:B43) -> 0 | C44: =SUM(C41:C43) -> 0 | D44: =SUM(D41:D43) -> 0 | E44: =SUM(E41:E43) -> 0 | F44: =SUM(F41:F43) -> 0 | G44: =SUM(G41:G43) -> 0 | H44: =SUM(H41:H43) -> 0 | I44: =SUM(I41:I43) -> 0 | ... M44: =SUM(M41:M43) -> 0 | N44: =SUM(B44:M44) -> 0
A46: B. Fixed Term Assets
A47: Furniture, Machinery and Equipment | B47: =Transactions!B65+Transactions!B66+Transactions!B67 -> 0 | C47: =Transactions!C65+Transactions!C66+Transactions!C67 -> 0 | D47: =Transactions!D65+Transactions!D66+Transactions!D67 -> 0 | E47: =Transactions!E65+Transactions!E66+Transactions!E67 -> 0 | F47: =Transactions!F65+Transactions!F66+Transactions!F67 -> 0 | G47: =Transactions!G65+Transactions!G66+Transactions!G67 -> 0 | H47: =Transactions!H65+Transactions!H66+Transactions!H67 -> 0 | I47: =Transactions!I65+Transactions!I66+Transactions!I67 -> 0 | ... M47: =Transactions!M65+Transactions!M66+Transactions!M67 -> 0 | N47: =SUM(B47:M47) -> 0
A48: Vehicles | B48: =Transactions!B68 -> 0 | C48: =Transactions!C68 -> 0 | D48: =Transactions!D68 -> 0 | E48: =Transactions!E68 -> 0 | F48: =Transactions!F68 -> 0 | G48: =Transactions!G68 -> 0 | H48: =Transactions!H68 -> 0 | I48: =Transactions!I68 -> 0 | ... M48: =Transactions!M68 -> 0 | N48: =SUM(B48:M48) -> 0
A49: Land and Building | B49: =Transactions!B69+Transactions!B70 -> 0 | C49: =Transactions!C69+Transactions!C70 -> 0 | D49: =Transactions!D69+Transactions!D70 -> 0 | E49: =Transactions!E69+Transactions!E70 -> 0 | F49: =Transactions!F69+Transactions!F70 -> 0 | G49: =Transactions!G69+Transactions!G70 -> 0 | H49: =Transactions!H69+Transactions!H70 -> 0 | I49: =Transactions!I69+Transactions!I70 -> 0 | ... M49: =Transactions!M69+Transactions!M70 -> 0 | N49: =SUM(B49:M49) -> 0
A50: Total Fixed Assets | B50: =SUM(B47:B49) -> 0 | C50: =SUM(C47:C49) -> 0 | D50: =SUM(D47:D49) -> 0 | E50: =SUM(E47:E49) -> 0 | F50: =SUM(F47:F49) -> 0 | G50: =SUM(G47:G49) -> 0 | H50: =SUM(H47:H49) -> 0 | I50: =SUM(I47:I49) -> 0 | ... M50: =SUM(M47:M49) -> 0 | N50: =SUM(B50:M50) -> 0
A52: Total Assets (A+B) | B52: =B44+B50 -> 0 | C52: =C44+C50 -> 0 | D52: =D44+D50 -> 0 | E52: =E44+E50 -> 0 | F52: =F44+F50 -> 0 | G52: =G44+G50 -> 0 | H52: =H44+H50 -> 0 | I52: =I44+I50 -> 0 | ... M52: =M44+M50 -> 0 | N52: =SUM(B52:M52) -> 0
A54: Liabilities and Equity
A55: C. Current Liability
A56: Loans Payable < 12 months | B56: =Transactions!B53 -> 0 | C56: =Transactions!C53 -> 0 | D56: =Transactions!D53 -> 0 | E56: =Transactions!E53 -> 0 | F56: =Transactions!F53 -> 0 | G56: =Transactions!G53 -> 0 | H56: =Transactions!H53 -> 0 | I56: =Transactions!I53 -> 0 | ... M56: =Transactions!M53 -> 0 | N56: =SUM(B56:M56) -> 0
A57: Commissions due | B57: =Transactions!B54 -> 0 | C57: =Transactions!C54 -> 0 | D57: =Transactions!D54 -> 0 | E57: =Transactions!E54 -> 0 | F57: =Transactions!F54 -> 0 | G57: =Transactions!G54 -> 0 | H57: =Transactions!H54 -> 0 | I57: =Transactions!I54 -> 0 | ... M57: =Transactions!M54 -> 0 | N57: =SUM(B57:M57) -> 0
A58: Payments to providers | B58: =Transactions!B55 -> 0 | C58: =Transactions!C55 -> 0 | D58: =Transactions!D55 -> 0 | E58: =Transactions!E55 -> 0 | F58: =Transactions!F55 -> 0 | G58: =Transactions!G55 -> 0 | H58: =Transactions!H55 -> 0 | I58: =Transactions!I55 -> 0 | ... M58: =Transactions!M55 -> 0 | N58: =SUM(B58:M58) -> 0
A59: Taxes and fees due | B59: =Transactions!B56 -> 0 | C59: =Transactions!C56 -> 0 | D59: =Transactions!D56 -> 0 | E59: =Transactions!E56 -> 0 | F59: =Transactions!F56 -> 0 | G59: =Transactions!G56 -> 0 | H59: =Transactions!H56 -> 0 | I59: =Transactions!I56 -> 0 | ... M59: =Transactions!M56 -> 0 | N59: =SUM(B59:M59) -> 0
A60: Total Current Liability | B60: =SUM(B56:B59) -> 0 | C60: =SUM(C56:C59) -> 0 | D60: =SUM(D56:D59) -> 0 | E60: =SUM(E56:E59) -> 0 | F60: =SUM(F56:F59) -> 0 | G60: =SUM(G56:G59) -> 0 | H60: =SUM(H56:H59) -> 0 | I60: =SUM(I56:I59) -> 0 | ... M60: =SUM(M56:M59) -> 0 | N60: =SUM(B60:M60) -> 0
A62: D. Non-current Liability
A63: Loans Payable > 12 months | B63: =Transactions!B60 -> 0 | C63: =Transactions!C60 -> 0 | D63: =Transactions!D60 -> 0 | E63: =Transactions!E60 -> 0 | F63: =Transactions!F60 -> 0 | G63: =Transactions!G60 -> 0 | H63: =Transactions!H60 -> 0 | I63: =Transactions!I60 -> 0 | ... M63: =Transactions!M60 -> 0 | N63: =SUM(B63:M63) -> 0
A64: Non-Bank >12months | B64: =Transactions!B61 -> 0 | C64: =Transactions!C61 -> 0 | D64: =Transactions!D61 -> 0 | E64: =Transactions!E61 -> 0 | F64: =Transactions!F61 -> 0 | G64: =Transactions!G61 -> 0 | H64: =Transactions!H61 -> 0 | I64: =Transactions!I61 -> 0 | ... M64: =Transactions!M61 -> 0 | N64: =SUM(B64:M64) -> 0
A65: Total non-current liability | B65: =B63+B64 -> 0 | C65: =C63 -> 0 | D65: =D63 -> 0 | E65: =E63 -> 0 | F65: =F63 -> 0 | G65: =G63 -> 0 | H65: =H63 -> 0 | I65: =I63 -> 0 | J65: =J63 -> 0 | ... M65: =M63 -> 0 | N65: =SUM(B65:M65) -> 0
A67: Total Liability (C+D) | B67: =B65+B60 -> 0 | C67: =C65+C60 -> 0 | D67: =D65+D60 -> 0 | E67: =E65+E60 -> 0 | F67: =F65+F60 -> 0 | G67: =G65+G60 -> 0 | H67: =H65+H60 -> 0 | I67: =I65+I60 -> 0 | ... M67: =M65+M60 -> 0 | N67: =SUM(B67:M67) -> 0
A69: Equity
A70: Owner's (or shareholders') equity | B70: =B52-B67-B37 -> 0 | C70: =C52-C67-C37 -> 0 | D70: =D52-D67-D37 -> 0 | E70: =E52-E67-E37 -> 0 | F70: =F52-F67-F37 -> 0 | G70: =G52-G67-G37 -> 0 | H70: =H52-H67-H37 -> 0 | I70: =I52-I67-I37 -> 0 | ... M70: =M52-M67-M37 -> 0 | N70: =SUM(B70:M70) -> 0
A71: Net Income | B71: =B37 -> 0 | C71: =C37 -> 0 | D71: =D37 -> 0 | E71: =E37 -> 0 | F71: =F37 -> 0 | G71: =G37 -> 0 | H71: =H37 -> 0 | I71: =I37 -> 0 | ... M71: =M37 -> 0 | N71: =SUM(B71:M71) -> 0
A72: Total Equity | B72: =B70+B71 -> 0 | C72: =C70+C71 -> 0 | D72: =D70+D71 -> 0 | E72: =E70+E71 -> 0 | F72: =F70+F71 -> 0 | G72: =G70+G71 -> 0 | H72: =H70+H71 -> 0 | I72: =I70+I71 -> 0 | ... M72: =M70+M71 -> 0 | N72: =SUM(B72:M72) -> 0
A73: Total Liabilities and Equities | B73: =B67+B72 -> 0 | C73: =C67+C72 -> 0 | D73: =D67+D72 -> 0 | E73: =E67+E72 -> 0 | F73: =F67+F72 -> 0 | G73: =G67+G72 -> 0 | H73: =H67+H72 -> 0 | I73: =I67+I72 -> 0 | ... M73: =M67+M72 -> 0 | N73: =SUM(B73:M73) -> 0
A75: Financial Analysis - ratios
A76: 1. Activity Ratio
A77: Inventory Turnover | B77: =Transactions!B7/Transactions!B46 -> #DIV/0! | C77: =Transactions!C7/Transactions!C46 -> #DIV/0! | D77: =Transactions!D7/Transactions!D46 -> #DIV/0! | E77: =Transactions!E7/Transactions!E46 -> #DIV/0! | F77: =Transactions!F7/Transactions!F46 -> #DIV/0! | G77: =Transactions!G7/Transactions!G46 -> #DIV/0! | H77: =Transactions!H7/Transactions!H46 -> #DIV/0! | I77: =Transactions!I7/Transactions!I46 -> #DIV/0! | ... N77: =Transactions!N7/Transactions!N46 -> #DIV/0!
A78: Receivables Turnover | B78: =Transactions!B43*365/Transactions!B7 -> #DIV/0! | C78: =Transactions!C43/Transactions!C7 -> #DIV/0! | D78: =Transactions!D43/Transactions!D7 -> #DIV/0! | E78: =Transactions!E43/Transactions!E7 -> #DIV/0! | F78: =Transactions!F43/Transactions!F7 -> #DIV/0! | G78: =Transactions!G43/Transactions!G7 -> #DIV/0! | H78: =Transactions!H43/Transactions!H7 -> #DIV/0! | I78: =Transactions!I43/Transactions!I7 -> #DIV/0! | J78: =Transactions!J43/Transactions!J7 -> #DIV/0! | ... N78: =Transactions!N43/Transactions!N7 -> #DIV/0!
A80: 2. Liquidity
A81: Current ratio | B81: =B44/B60 -> #DIV/0! | C81: ='FInancial Statements'!C44/'FInancial Statements'!C60 -> #DIV/0! | D81: ='FInancial Statements'!D44/'FInancial Statements'!D60 -> #DIV/0! | E81: ='FInancial Statements'!E44/'FInancial Statements'!E60 -> #DIV/0! | F81: ='FInancial Statements'!F44/'FInancial Statements'!F60 -> #DIV/0! | G81: ='FInancial Statements'!G44/'FInancial Statements'!G60 -> #DIV/0! | H81: ='FInancial Statements'!H44/'FInancial Statements'!H60 -> #DIV/0! | I81: ='FInancial Statements'!I44/'FInancial Statements'!I60 -> #DIV/0! | J81: ='FInancial Statements'!J44/'FInancial Statements'!J60 -> #DIV/0! | ... N81: ='FInancial Statements'!N44/'FInancial Statements'!N60 -> #DIV/0!
A82: Acid test (quick ratio) | B82: =(B44-B43)/B60 -> #DIV/0! | C82: =(C44-C43)/C60 -> #DIV/0! | D82: =(D44-D43)/D60 -> #DIV/0! | E82: =(E44-E43)/E60 -> #DIV/0! | F82: =(F44-F43)/F60 -> #DIV/0! | G82: =(G44-G43)/G60 -> #DIV/0! | H82: =(H44-H43)/H60 -> #DIV/0! | I82: =(I44-I43)/I60 -> #DIV/0! | ... N82: =(N44-N43)/N60 -> #DIV/0!
A84: 3. Debt
A85: Debt on Assets | B85: =B67/B52 -> #DIV/0! | C85: =C67/C52 -> #DIV/0! | D85: =D67/D52 -> #DIV/0! | E85: =E67/E52 -> #DIV/0! | F85: =F67/F52 -> #DIV/0! | G85: =G67/G52 -> #DIV/0! | H85: =H67/H52 -> #DIV/0! | I85: =I67/I52 -> #DIV/0! | ... N85: =N67/N52 -> #DIV/0!
A86: Debt-equity ratio | B86: =B67/B72 -> #DIV/0! | C86: =C67/C72 -> #DIV/0! | D86: =D67/D72 -> #DIV/0! | E86: =E67/E72 -> #DIV/0! | F86: =F67/F72 -> #DIV/0! | G86: =G67/G72 -> #DIV/0! | H86: =H67/H72 -> #DIV/0! | I86: =I67/I72 -> #DIV/0! | ... N86: =N67/N72 -> #DIV/0!
A88: 4. Profitability
A89: ROA (Return on Assets) | B89: =B71/B52*100 -> #DIV/0! | C89: =C37/C51*100 -> #DIV/0! | D89: =D37/D51*100 -> #DIV/0! | E89: =E37/E51*100 -> #DIV/0! | F89: =F37/F51*100 -> #DIV/0! | G89: =G37/G51*100 -> #DIV/0! | H89: =H37/H51*100 -> #DIV/0! | I89: =I37/I51*100 -> #DIV/0! | J89: =J37/J51*100 -> #DIV/0! | ... N89: =N37/N51*100 -> #DIV/0!
A90: ROE (Return on Equity) | B90: =B37/B70*100 -> #DIV/0! | C90: =C37/C70*100 -> #DIV/0! | D90: =D37/D70*100 -> #DIV/0! | E90: =E37/E70*100 -> #DIV/0! | F90: =F37/F70*100 -> #DIV/0! | G90: =G37/G70*100 -> #DIV/0! | H90: =H37/H70*100 -> #DIV/0! | I90: =I37/I70*100 -> #DIV/0! | ... N90: =N37/N70*100 -> #DIV/0!
A92: 5. Others
A93: Working Capital | B93: =B44-B60 -> 0 | C93: =C44-C60 -> 0 | D93: =D44-D60 -> 0 | E93: =E44-E60 -> 0 | F93: =F44-F60 -> 0 | G93: =G44-G60 -> 0 | H93: =H44-H60 -> 0 | I93: =I44-I60 -> 0 | ... M93: =M44-M60 -> 0 | N93: =SUM(B93:M93) -> 0
A94: Net Profit Margin | B94: =B37/B28*100 -> #DIV/0! | C94: =C37/C28*100 -> #DIV/0! | D94: =D37/D28*100 -> #DIV/0! | E94: =E37/E28*100 -> #DIV/0! | F94: =F37/F28*100 -> #DIV/0! | G94: =G37/G28*100 -> #DIV/0! | H94: =H37/H28*100 -> #DIV/0! | I94: =I37/I28*100 -> #DIV/0! | ... N94: =N37/N28*100 -> #DIV/0!
